<?xml version="1.0"?>

<model-hints>
	<model name="com.reportssent.plugins.model.Reports">
		<field name="uuid" type="String" />
		<field name="statusId" type="long" />
		<field name="groupId" type="long" />
		<field name="companyId" type="long" />
		<field name="userId" type="long" />
		<field name="userName" type="String" />
		<field name="createDate" type="Date" />
		<field name="modifiedDate" type="Date" />
		<field name="statusName" type="String" />
		<field name="statusValue" type="String" />
	</model>
</model-hints>